BUILD.md
LICENSE.txt
MANIFEST.in
README.md
README.rst
cx.py
setup.py
stdeb.cfg
LICENSES/Open Game License 1.0a.txt
LICENSES/SIL Open Font Lincense.txt
LICENSES/apache-2.0.txt
LICENSES/bsd.txt
LICENSES/cc-by-3.0.txt
LICENSES/lgpl-2.1.txt
LICENSES/mit.txt
LICENSES/psf-license.txt
archlinux/PKGBUILD
src/pySpellbook.desktop
src/icons/application-exit.png
src/icons/document-new.png
src/icons/document-open.png
src/icons/document-save-as.png
src/icons/document-save.png
src/icons/icons.qrc
src/icons/list-add.png
src/icons/office-book.png
src/icons/preferences-system.png
src/icons/pySpellbook.icns
src/icons/pySpellbook.ico
src/icons/pySpellbook.png
src/icons/pySpellbook.svg
src/pySpellbook/__init__.py
src/pySpellbook/addSpellWindow.py
src/pySpellbook/bw_icons_rc.py
src/pySpellbook/config_window.py
src/pySpellbook/db.py
src/pySpellbook/firstRunWizard.py
src/pySpellbook/icons_rc.py
src/pySpellbook/importTools.py
src/pySpellbook/models.py
src/pySpellbook/newMainWindow.py
src/pySpellbook/qmodel.py
src/pySpellbook/qtpdf.py
src/pySpellbook/run.py
src/pySpellbook/template.py
src/pySpellbook.egg-info/PKG-INFO
src/pySpellbook.egg-info/SOURCES.txt
src/pySpellbook.egg-info/dependency_links.txt
src/pySpellbook.egg-info/requires.txt
src/pySpellbook.egg-info/top_level.txt
src/pySpellbook/i18n/de_DE.qm
src/pySpellbook/i18n/de_DE.ts
src/pySpellbook/i18n/en_US.ts
src/pySpellbook/i18n/pySpellbook.pro
src/pySpellbook/templates/html/template.html
src/pySpellbook/templates/html/resources/ecke.png
src/pySpellbook/templates/html/resources/ecke.svg
src/pySpellbook/templates/html/resources/ecke.xcf
src/pySpellbook/templates/html/resources/ecke2.png
src/pySpellbook/templates/html/resources/ecke3.png
src/pySpellbook/templates/html/resources/ecke3_.png
src/pySpellbook/templates/html/resources/ecke4.png
src/pySpellbook/templates/html/resources/ecke_.png
src/pySpellbook/templates/html/resources/html.css
src/pySpellbook/templates/html/resources/humanistic.ttf
src/pySpellbook/templates/html/resources/line1.pdf
src/pySpellbook/templates/html/resources/line1.png
src/pySpellbook/templates/html/resources/line2.pdf
src/pySpellbook/templates/html/resources/line2.png
