Metadata-Version: 1.1
Name: pySpellbook
Version: 0.9
Summary: A PDF spellbook creation utility for d20 games in python
Home-page: https://github.com/christofsteel/pyspellbook
Author: Christoph Stahl
Author-email: christoph.stahl@uni-dortmund.de
License: apache2
Platform: posix
Platform: win32
Platform: win64
Classifier: Development Status :: 4 - Beta
Classifier: Intended Audience :: End Users/Desktop
Classifier: License :: OSI Approved :: Apache Software License
Classifier: Operating System :: Microsoft :: Windows
Classifier: Operating System :: POSIX
Classifier: Topic :: Games/Entertainment :: Role-Playing
